pyisocapi/__init__.py
pyisocapi/client.py
pyisocapi/constants.py
pyisocapi/exceptions.py
pyisocapi/response.py
pyisocapi/payloads/otodom.py
pyisocapi/payloads/vinted.py
pyisocapi-0.0.3.dist-info/LICENSE
pyisocapi-0.0.3.dist-info/METADATA
pyisocapi-0.0.3.dist-info/WHEEL
pyisocapi-0.0.3.dist-info/top_level.txt
pyisocapi-0.0.3.dist-info/RECORD
