Metadata-Version: 2.1
Name: pyisocapi
Version: 0.0.3
Summary: Python Isocapi API wrapper
Author-email: isocapi@gmail.com
Project-URL: Homepage, https://isocapi.com/
Project-URL: Repository, https://github.com/isocsoft/pyisocapi.git
Project-URL: Issues, https://github.com/isocsoft/pyisocapi/issues
Classifier: Programming Language :: Python :: 3
Classifier: License :: OSI Approved :: MIT License
Requires-Python: >=3.10
License-File: LICENSE
Requires-Dist: niquests >=3.7.2
Provides-Extra: test
Requires-Dist: parameterized ; extra == 'test'
Requires-Dist: ruff ; extra == 'test'
Requires-Dist: pre-commit ; extra == 'test'
